pfpy/__init__.py
pfpy/models.py
pfpy/pf.py
pfpy/wavegen.py
pfpy-0.0.2.dist-info/LICENSE
pfpy-0.0.2.dist-info/METADATA
pfpy-0.0.2.dist-info/WHEEL
pfpy-0.0.2.dist-info/top_level.txt
pfpy-0.0.2.dist-info/RECORD
