Metadata-Version: 2.1
Name: pfpy
Version: 0.0.2
Summary: Power Factory with Python
Home-page: https://github.com/tinrabuzin/PFPy
Author: Tin Rabuzin
Author-email: trabuzin@gmail.com
License: UNKNOWN
Platform: UNKNOWN
Classifier: Programming Language :: Python :: 3
Classifier: License :: OSI Approved :: MIT License
Classifier: Operating System :: OS Independent
Requires-Python: >=3.7
Requires-Dist: pandas
Requires-Dist: numpy
Requires-Dist: matplotlib
Requires-Dist: scipy
